{
  "type": "electrodynamics:oxidation_furnace_recipe",
  "experience": 0.30000001192092896,
  "itembi": {
    "0": {
      "chance": 0.75,
      "count": 1,
      "item": "electrodynamics:slag"
    },
    "count": 1
  },
  "iteminputs": {
    "0": {
      "count": 1,
      "tag": "forge:oxide/chromium"
    },
    "1": {
      "count": 1,
      "tag": "forge:oxide/calciumcarbonate"
    },
    "count": 2
  },
  "output": {
    "count": 1,
    "item": "electrodynamics:ingotchromium"
  },
  "ticks": 200,
  "usagepertick": 350.0
}