{
    "display": {
        "title": {
            "text": "Dual Milling",
            "color": "blue"
        },
        "description": {
            "text": "Make a double wire mill!"
        },
        "icon": {
            "item": "electrodynamics:wiremilldouble"
        },
        "frame": "task",
        "show_toast": true,
        "announce_to_chat": true,
        "hidden": false
    },
    "criteria": {
        "HasMill": {
            "trigger": "minecraft:inventory_changed",
            "conditions": {
                "items": [
                    {
                        "items": [ "electrodynamics:wiremilldouble"]
                    }
                ]
            }
        }
    },
    "requirements": [
        [
            "HasMill"
        ]
    ],
    "rewards": {
        "experience": 50
    },
    "parent": "electrodynamics:wiremill"
}