{
  "parent": "electrodynamics:ores",
  "display": {
    "icon": {
      "item": "electrodynamics:oretin"
    },
    "title": {
      "color": "gray",
      "translate": "advancement.electrodynamics.tinore.title"
    },
    "description": {
      "translate": "advancement.electrodynamics.tinore.desc"
    },
    "frame": "task",
    "show_toast": true,
    "announce_to_chat": true,
    "hidden": false
  },
  "rewards": {
    "experience": 10
  },
  "criteria": {
    "HasRawOre": {
      "trigger": "minecraft:inventory_changed",
      "conditions": {
        "items": [
          {
            "item": "electrodynamics:oretin"
          }
        ]
      }
    }
  },
  "requirements": [
    [
      "HasRawOre"
    ]
  ]
}